{
	"class" : {
		 },
	"instance" : {
		"add:" : "JurajKubelka 3/18/2014 17:01",
		"addAssociation:" : "JurajKubelka 3/26/2014 10:29",
		"addCompiledMethod:" : "JurajKubelka 3/26/2014 10:57",
		"addFilter:" : "JurajKubelka 3/14/2014 11:22",
		"addImplementorsOf:from:" : "JurajKubelka 3/18/2014 13:42",
		"addImplementorsOfAst:from:" : "JurajKubelka 4/22/2014 16:50",
		"addNodeFromModel:" : "JurajKubelka 3/26/2014 10:57",
		"addSendersOf:" : "JurajKubelka 4/29/2014 16:07",
		"allAccessesTo:from:" : "JurajKubelka 5/5/2014 09:06",
		"announcer" : "JurajKubelka 3/10/2014 17:47",
		"archivist" : "JurajKubelka 3/10/2014 19:56",
		"civilEngineer" : "JurajKubelka 3/11/2014 14:50",
		"cloner" : "JurajKubelka 3/10/2014 19:37",
		"cobweb" : "JurajKubelka 3/10/2014 19:06",
		"edgeCatcher" : "JurajKubelka 3/11/2014 15:29",
		"edgeDustman" : "JurajKubelka 3/11/2014 17:18",
		"filterAdmin" : "JurajKubelka 3/13/2014 13:34",
		"filterItem:" : "JurajKubelka 3/13/2014 15:57",
		"journalist" : "JurajKubelka 3/10/2014 17:47",
		"methodCatcher" : "JurajKubelka 3/11/2014 14:52",
		"nodeDustman" : "JurajKubelka 3/11/2014 17:18",
		"redo" : "JurajKubelka 4/1/2014 14:43",
		"remove:" : "JurajKubelka 7/25/2014 15:09",
		"removeFilter:" : "JurajKubelka 3/13/2014 15:58",
		"removeNode:" : "JurajKubelka 3/18/2014 13:42",
		"setCobweb:" : "JurajKubelka 3/11/2014 14:27",
		"statist" : "JurajKubelka 3/10/2014 19:15",
		"strategist" : "JurajKubelka 3/13/2014 13:18",
		"systemExpert" : "JurajKubelka 3/14/2014 10:01",
		"troopClass" : "JurajKubelka 3/18/2014 11:58",
		"undo" : "JurajKubelka 4/1/2014 14:43" } }
